arise/__init__.py
arise/configs.py
arise/core.py
arise/schemas.yml
arise/commands/__init__.py
arise/commands/auth.py
arise/commands/build.py
arise/commands/clean.py
arise/commands/dashboard.py
arise/commands/deploy.py
arise/commands/pull.py
arise/shadows/__init__.py
arise/shadows/bellion.py
arise/shadows/igris.py
arise/shadows/tusk.py
arise/types/__init__.py
arise/types/blockchain_info.py
arise/types/build.py
arise/types/chain.py
arise/types/difficulty_adjustment.py
arise/types/mempool_info.py
arise/types/service.py
arise-0.2.3.dist-info/METADATA
arise-0.2.3.dist-info/WHEEL
arise-0.2.3.dist-info/entry_points.txt
arise-0.2.3.dist-info/licenses/LICENSE
arise-0.2.3.dist-info/RECORD
