Metadata-Version: 2.3
Name: arise
Version: 0.2.3
Summary: Running Bitcoin and peripherals via Terminal User Interface
Author-email: Sitt Guruvanich <aekasitt.g+github@siamintech.co.th>
License: MIT
Keywords: anonymous,bitcoin,cli,lightning,terminal,tui,ui,user-interface
Classifier: Development Status :: 3 - Alpha
Classifier: Environment :: Console
Classifier: Intended Audience :: Developers
Classifier: Intended Audience :: Financial and Insurance Industry
Classifier: License :: OSI Approved :: MIT License
Classifier: Operating System :: MacOS
Classifier: Operating System :: MacOS :: MacOS 9
Classifier: Operating System :: MacOS :: MacOS X
Classifier: Operating System :: OS Independent
Classifier: Operating System :: Unix
Classifier: Programming Language :: Python :: 3
Classifier: Programming Language :: Python :: 3 :: Only
Classifier: Programming Language :: Python :: 3.9
Classifier: Programming Language :: Python :: 3.10
Classifier: Programming Language :: Python :: 3.11
Classifier: Programming Language :: Python :: 3.12
Classifier: Programming Language :: Python :: 3.13
Classifier: Topic :: Office/Business :: Financial
Classifier: Topic :: Office/Business :: Financial :: Investment
Classifier: Topic :: Other/Nonlisted Topic
Classifier: Topic :: Security :: Cryptography
Requires-Python: >=3.8
Requires-Dist: apscheduler>=3.10.4
Requires-Dist: blessed>=1.20.0
Requires-Dist: click>=8.1.7
Requires-Dist: docker>=7.1.0
Requires-Dist: pydantic>=2.5.2
Requires-Dist: pyyaml>=6.0.1
Requires-Dist: rich>=13.7.0
